{"title":"计蒜客-蒜头君的旅游计划","uid":"27d37516f0a0b13306993a641101a6f8","slug":"计蒜客-蒜头君的旅游计划","date":"2021-08-01T06:19:00.000Z","updated":"2021-08-06T15:27:36.560Z","comments":true,"path":"api/articles/计蒜客-蒜头君的旅游计划.json","keywords":null,"cover":null,"content":"<p>奇怪的题面QAQ</p>\n<span id=\"more\"></span>\n\n<h3 id=\"题意概括\"><a href=\"#题意概括\" class=\"headerlink\" title=\"题意概括\"></a>题意概括</h3><p>马上就要放寒假了，蒜头君已经辛勤的工作一年了，打算和家人一起出去旅游放松放松。有经验的人一定知道，出去旅游前一定要有详细的旅行规划。蒜头君打算旅游 <em>n</em> 个城市，但并不是每条路线的花费都是一样的。蒜头君是一个勤俭节俭的人，他就在想怎么把所有的城市旅游一遍花费最小呢？（蒜头君不喜欢重复旅游同一个城市，也就是说已到达过的城市蒜头君是不会再次光临的）求从1号城市出发，经过所有景点且不重复，最后回到起点的最小花费。</p>\n<h3 id=\"题目分析\"><a href=\"#题目分析\" class=\"headerlink\" title=\"题目分析\"></a>题目分析</h3><p>题面写得很迷啊…说是先旅行经过每个城市，然后再返回起点——事实上回来的时候不用找回起点的最短路，而是最终到达哪个城市就直接从那个城市返回起点就行了。</p>\n<p>所以依旧是老做法，从起点开始搜，找到一个终点，使得所有点都被访问过且从起点经过其他点到达终点、再从终点直接返回起点的距离和最小即可。注意剪枝。/</p>\n<h3 id=\"代码\"><a href=\"#代码\" class=\"headerlink\" title=\"代码\"></a>代码</h3><pre class=\"line-numbers language-cpp\" data-language=\"cpp\"><code class=\"language-cpp\">#include &lt;bits/stdc++.h&gt;\n#define int long long\n#define maxn 20\nusing namespace std;\n\nint read() {\n\tchar c = getchar();\n\tint f = 1, _ = 0;\n\twhile (c &gt; '9' || c &lt; '0')\n\t\tf = (c == '-') ? -1 : 1, c = getchar();\n\twhile (c &lt;= '9' &amp;&amp; c &gt;= '0')\n\t\t_ = (_ &lt;&lt; 3) + (_ &lt;&lt; 1) + (c ^ 48), c = getchar();\n\treturn _ * f;\n}\nint n;\nint a[maxn][maxn];\nint flag[maxn];\nint ans = 0x3f3f3f3f;\n\nvoid dfs(int now, int dis, int need) {\n\t//cout &lt;&lt; now &lt;&lt; \" \" &lt;&lt; dis &lt;&lt; \" \" &lt;&lt; need &lt;&lt; endl;\n\tif (dis &gt; ans)\n\t\treturn;\n\tif (need == 0) {\n\t\tans = min(ans, dis + a[now][0]);\n\t\treturn;\n\t}\n\tflag[now] = 1;\n\tfor (register int i = 0; i &lt; n; i++) {\n\t\tif (flag[i])\n\t\t\tcontinue;\n\t\tdfs(i, dis + a[now][i], need - 1);\n\t}\n\tflag[now] = 0;\n\treturn;\n}\n\nsigned main() {\n\tn = read();\n\tfor (register int i = 0; i &lt; n; i++) {\n\t\tfor (register int j = 0; j &lt; n; j++) {\n\t\t\ta[i][j] = read();\n\t\t}\n\t}\n\tdfs(0, 0, n - 1);\n\tcout &lt;&lt; ans  &lt;&lt; endl;\n\treturn 0;\n}</code></pre>\n\n","text":"奇怪的题面QAQ 题意概括马上就要放寒假了，蒜头君已经辛勤的工作一年了，打算和家人一起出去旅游放松放松。有经验的人一定知道，出去旅游前一定要有详细的旅行规划。蒜头君打算旅游 n 个城市，但并不是每条路线的花费都是一样的。蒜头君是一个勤俭节俭的人，他就在想怎么把所有的城市旅游一遍花...","link":"","photos":[],"count_time":{"symbolsCount":"1.4k","symbolsTime":"1 mins."},"categories":[{"name":"题解","slug":"题解","count":33,"path":"api/categories/题解.json"}],"tags":[{"name":"恢复OI实力","slug":"恢复OI实力","count":23,"path":"api/tags/恢复OI实力.json"},{"name":"搜索","slug":"搜索","count":9,"path":"api/tags/搜索.json"},{"name":"算法裸题","slug":"算法裸题","count":7,"path":"api/tags/算法裸题.json"}],"toc":"<ol class=\"toc\"><li class=\"toc-item toc-level-3\"><a class=\"toc-link\" href=\"#%E9%A2%98%E6%84%8F%E6%A6%82%E6%8B%AC\"><span class=\"toc-text\">题意概括</span></a></li><li class=\"toc-item toc-level-3\"><a class=\"toc-link\" href=\"#%E9%A2%98%E7%9B%AE%E5%88%86%E6%9E%90\"><span class=\"toc-text\">题目分析</span></a></li><li class=\"toc-item toc-level-3\"><a class=\"toc-link\" href=\"#%E4%BB%A3%E7%A0%81\"><span class=\"toc-text\">代码</span></a></li></ol>","author":{"name":"白泽","slug":"blog-author","avatar":"https://img-blog.csdnimg.cn/20210313122054101.png","link":"/","description":"一个正在追逐游戏开发梦的大学生！","socials":{"github":"","twitter":"","stackoverflow":"","wechat":"","qq":"","weibo":"","zhihu":"","csdn":"","juejin":"","customs":{"bilibili":{"icon":"/svg/Bilibili.svg","link":"https://space.bilibili.com/91730547"},"zhihu":{"icon":"/svg/Zhihu.svg","link":"https://www.zhihu.com/people/ying-zong-pai-wu-seng"}}}},"mapped":true,"prev_post":{"title":"计蒜客-等边三角形","uid":"87a7cd6516d80ea05ca08acaf34a19ee","slug":"计蒜客-等边三角形","date":"2021-08-02T06:19:00.000Z","updated":"2021-08-06T15:28:49.005Z","comments":true,"path":"api/articles/计蒜客-等边三角形.json","keywords":null,"cover":null,"text":"我说我刚开始学编程那段儿就没学好搜索你信么？就这题我都想了一刻钟。 题意概括蒜头君手上有一些小木棍，它们长短不一，蒜头君想用这些木棍拼出一个等边三角形，并且每根木棍都要用到。 例如，蒜头君手上有长度为 1，2，3，3的4根木棍，他可以让长度为1，2的木棍组成一条边，另外2跟分别组...","link":"","photos":[],"count_time":{"symbolsCount":"1.7k","symbolsTime":"2 mins."},"categories":[{"name":"题解","slug":"题解","count":33,"path":"api/categories/题解.json"}],"tags":[{"name":"恢复OI实力","slug":"恢复OI实力","count":23,"path":"api/tags/恢复OI实力.json"},{"name":"搜索","slug":"搜索","count":9,"path":"api/tags/搜索.json"},{"name":"算法裸题","slug":"算法裸题","count":7,"path":"api/tags/算法裸题.json"}],"author":{"name":"白泽","slug":"blog-author","avatar":"https://img-blog.csdnimg.cn/20210313122054101.png","link":"/","description":"一个正在追逐游戏开发梦的大学生！","socials":{"github":"","twitter":"","stackoverflow":"","wechat":"","qq":"","weibo":"","zhihu":"","csdn":"","juejin":"","customs":{"bilibili":{"icon":"/svg/Bilibili.svg","link":"https://space.bilibili.com/91730547"},"zhihu":{"icon":"/svg/Zhihu.svg","link":"https://www.zhihu.com/people/ying-zong-pai-wu-seng"}}}}},"next_post":{"title":"洛谷P1089-津津的储蓄计划","uid":"e0205a08963cdeb73a523932f7b01f71","slug":"洛谷P1089-津津的储蓄计划","date":"2021-08-01T04:27:11.000Z","updated":"2021-08-06T15:27:55.131Z","comments":true,"path":"api/articles/洛谷P1089-津津的储蓄计划.json","keywords":null,"cover":null,"text":"找手感的入门题目~ 题意概括津津的零花钱一直都是自己管理。每个月的月初妈妈给津津300元钱，津津会预算这个月的花销，并且总能做到实际花销和预算的相同。 为了让津津学习如何储蓄，妈妈提出，津津可以随时把整百的钱存在她那里，到了年末她会加上%20还给津津。因此津津制定了一个储蓄计划：...","link":"","photos":[],"count_time":{"symbolsCount":"1.3k","symbolsTime":"1 mins."},"categories":[{"name":"题解","slug":"题解","count":33,"path":"api/categories/题解.json"}],"tags":[{"name":"恢复OI实力","slug":"恢复OI实力","count":23,"path":"api/tags/恢复OI实力.json"},{"name":"模拟","slug":"模拟","count":5,"path":"api/tags/模拟.json"},{"name":"NOIP真题","slug":"NOIP真题","count":5,"path":"api/tags/NOIP真题.json"}],"author":{"name":"白泽","slug":"blog-author","avatar":"https://img-blog.csdnimg.cn/20210313122054101.png","link":"/","description":"一个正在追逐游戏开发梦的大学生！","socials":{"github":"","twitter":"","stackoverflow":"","wechat":"","qq":"","weibo":"","zhihu":"","csdn":"","juejin":"","customs":{"bilibili":{"icon":"/svg/Bilibili.svg","link":"https://space.bilibili.com/91730547"},"zhihu":{"icon":"/svg/Zhihu.svg","link":"https://www.zhihu.com/people/ying-zong-pai-wu-seng"}}}}}}